LICENSE
MANIFEST.in
README.md
setup.py
RAPIDpy/__init__.py
RAPIDpy/dataset.py
RAPIDpy/helper_functions.py
RAPIDpy/rapid.py
RAPIDpy/utilities.py
RAPIDpy.egg-info/PKG-INFO
RAPIDpy.egg-info/SOURCES.txt
RAPIDpy.egg-info/dependency_links.txt
RAPIDpy.egg-info/requires.txt
RAPIDpy.egg-info/top_level.txt
RAPIDpy/gis/__init__.py
RAPIDpy/gis/centroid.py
RAPIDpy/gis/muskingum.py
RAPIDpy/gis/network.py
RAPIDpy/gis/taudem.py
RAPIDpy/gis/voronoi.py
RAPIDpy/gis/weight.py
RAPIDpy/gis/workflow.py
RAPIDpy/gis/lsm_grids/runoff_ecmwf_t1279_grid.nc
RAPIDpy/gis/lsm_grids/runoff_ecmwf_tco639_grid.nc
RAPIDpy/gis/lsm_grids/runoff_era_t511_grid.nc
RAPIDpy/inflow/CreateInflowFileFromERAInterimRunoff.py
RAPIDpy/inflow/CreateInflowFileFromGriddedRunoff.py
RAPIDpy/inflow/CreateInflowFileFromLDASRunoff.py
RAPIDpy/inflow/CreateInflowFileFromWRFHydroRunoff.py
RAPIDpy/inflow/__init__.py
RAPIDpy/inflow/lsm_rapid_process.py
RAPIDpy/postprocess/__init__.py
RAPIDpy/postprocess/generate_return_periods.py
RAPIDpy/postprocess/generate_seasonal_averages.py
RAPIDpy/postprocess/goodness_of_fit.py
RAPIDpy/postprocess/merge.py