Metadata-Version: 1.1
Name: RAPIDpy
Version: 2.6.0
Summary: Python interface for RAPID (rapid-hub.org)
Home-page: https://github.com/erdc-cm/RAPIDpy
Author: Alan Dee Snow
Author-email: alan.d.snow@usace.army.mil
License: BSD 3-Clause
Keywords: RAPID
Platform: UNKNOWN
Classifier: Intended Audience :: Developers
Classifier: Intended Audience :: Science/Research
Classifier: Operating System :: OS Independent
Classifier: Programming Language :: Python
Classifier: Programming Language :: Python :: 2
Classifier: Programming Language :: Python :: 2.7
Classifier: Programming Language :: Python :: 3
Classifier: Programming Language :: Python :: 3.5
Classifier: Programming Language :: Python :: 3.6
